odoo/addons/mis_builder_analytic/README.rst
odoo/addons/mis_builder_analytic/__init__.py
odoo/addons/mis_builder_analytic/__manifest__.py
odoo/addons/mis_builder_analytic/models/__init__.py
odoo/addons/mis_builder_analytic/models/mis_account_analytic_line.py
odoo/addons/mis_builder_analytic/readme/CONTRIBUTORS.rst
odoo/addons/mis_builder_analytic/readme/DESCRIPTION.rst
odoo/addons/mis_builder_analytic/readme/USAGE.rst
odoo/addons/mis_builder_analytic/security/ir.model.access.csv
odoo/addons/mis_builder_analytic/static/description/icon.png
odoo/addons/mis_builder_analytic/static/description/index.html
odoo/addons/mis_builder_analytic/views/mis_account_analytic_line_views.xml
odoo11_addon_mis_builder_analytic-11.0.1.0.0.99.dev4.dist-info/METADATA
odoo11_addon_mis_builder_analytic-11.0.1.0.0.99.dev4.dist-info/WHEEL
odoo11_addon_mis_builder_analytic-11.0.1.0.0.99.dev4.dist-info/top_level.txt
odoo11_addon_mis_builder_analytic-11.0.1.0.0.99.dev4.dist-info/RECORD
